protodocs/__init__.py
protodocs/_asgi.py
protodocs/_jsonschema.py
protodocs/_proto_docstrings.py
protodocs/_proto_specification.py
protodocs/_prototypes.py
protodocs/_specification.py
protodocs/_types.py
protodocs/_typesignature.py
protodocs/docsclient/NOTICE.txt
protodocs/docsclient/assets/favicon.png
protodocs/docsclient/b797181c93b3755f4fa1.ttf
protodocs/docsclient/editor.worker.js.gz
protodocs/docsclient/graphql.worker.worker.js.gz
protodocs/docsclient/index.html.gz
protodocs/docsclient/json.worker.js.gz
protodocs/docsclient/main.680dc52304c22666afc6.js.gz
protodocs/docsclient/web-licenses.txt
protodocs-0.1.0.dist-info/licenses/LICENSE
protodocs-0.1.0.dist-info/WHEEL
protodocs-0.1.0.dist-info/METADATA
protodocs-0.1.0.dist-info/RECORD
